{"ambientocclusion":false,"elements":[{"faces":{"down":{"texture":"#front","uv":[4,16,2,0]},"east":{"rotation":90,"texture":"#front","uv":[3,16,2,0]},"north":{"texture":"#front","uv":[2,0,4,1]},"south":{"rotation":180,"texture":"#front","uv":[2,1,4,0]},"up":{"rotation":180,"texture":"#front","uv":[2,0,4,16]},"west":{"rotation":90,"texture":"#front","uv":[4,0,3,16]}},"from":[12,8.5,-2.3995],"name":"Cube","rotation":{"angle":-45,"axis":"x","origin":[8,8,8]},"to":[14,9.5,20.6421]},{"faces":{"down":{"rotation":180,"texture":"#front","uv":[4,16,2,0]},"east":{"rotation":90,"texture":"#front","uv":[4,16,3,0]},"north":{"rotation":180,"texture":"#front","uv":[2,0,4,1]},"south":{"texture":"#front","uv":[2,1,4,0]},"up":{"texture":"#front","uv":[2,0,4,16]},"west":{"rotation":90,"texture":"#front","uv":[3,0,2,16]}},"from":[2,8.5,-2.39949],"name":"Cube","rotation":{"angle":-45,"axis":"x","origin":[8,8,8]},"to":[4,9.5,20.64214]},{"faces":{"down":{"rotation":180,"texture":"#front","uv":[2,13,1,15]},"east":{"rotation":90,"texture":"#front","uv":[14,13,15,15]},"north":{"rotation":180,"texture":"#front","uv":[1,13,2,14]},"south":{"rotation":180,"texture":"#front","uv":[2,14,1,15]},"up":{"texture":"#front","uv":[1,13,2,15]},"west":{"rotation":90,"texture":"#front","uv":[1,15,2,13]}},"from":[1,7.5,3.6],"name":"Cube","rotation":{"angle":-45,"axis":"x","origin":[8,8,8]},"to":[15,8.5,5.6]},{"faces":{"down":{"rotation":180,"texture":"#front","uv":[2,13,1,15]},"east":{"rotation":90,"texture":"#front","uv":[14,13,15,15]},"north":{"rotation":180,"texture":"#front","uv":[1,13,2,14]},"south":{"rotation":180,"texture":"#front","uv":[2,14,1,15]},"up":{"texture":"#front","uv":[1,13,2,15]},"west":{"rotation":90,"texture":"#front","uv":[1,15,2,13]}},"from":[1,7.5,-1.2],"name":"Cube","rotation":{"angle":-45,"axis":"x","origin":[8,8,8]},"to":[15,8.5,0.8]},{"faces":{"down":{"rotation":180,"texture":"#front","uv":[2,13,1,15]},"east":{"rotation":90,"texture":"#front","uv":[14,13,15,15]},"north":{"rotation":180,"texture":"#front","uv":[1,13,2,14]},"south":{"rotation":180,"texture":"#front","uv":[2,14,1,15]},"up":{"texture":"#front","uv":[1,13,2,15]},"west":{"rotation":90,"texture":"#front","uv":[1,15,2,13]}},"from":[1,7.5,8],"name":"Cube","rotation":{"angle":-45,"axis":"x","origin":[8,8,8]},"to":[15,8.5,10]},{"faces":{"down":{"rotation":180,"texture":"#front","uv":[2,13,1,15]},"east":{"rotation":90,"texture":"#front","uv":[14,13,15,15]},"north":{"rotation":180,"texture":"#front","uv":[1,13,2,14]},"south":{"rotation":180,"texture":"#front","uv":[2,14,1,15]},"up":{"texture":"#front","uv":[1,13,2,15]},"west":{"rotation":90,"texture":"#front","uv":[1,15,2,13]}},"from":[1,7.5,12.6],"name":"Cube","rotation":{"angle":-45,"axis":"x","origin":[8,8,8]},"to":[15,8.5,14.6]},{"faces":{"down":{"rotation":180,"texture":"#front","uv":[2,13,1,15]},"east":{"rotation":90,"texture":"#front","uv":[14,13,15,15]},"north":{"rotation":180,"texture":"#front","uv":[1,13,2,14]},"south":{"rotation":180,"texture":"#front","uv":[2,14,1,15]},"up":{"texture":"#front","uv":[1,13,2,15]},"west":{"rotation":90,"texture":"#front","uv":[1,15,2,13]}},"from":[1,7.5,17.2],"name":"Cube","rotation":{"angle":-45,"axis":"x","origin":[8,8,8]},"to":[15,8.5,19.2]},{"faces":{"down":{"texture":"#front","uv":[5,5,11,11]},"east":{"rotation":90,"texture":"#front","uv":[10,5,11,11]},"north":{"texture":"#front","uv":[11,5,5,6]},"south":{"texture":"#front","uv":[5,11,11,10]},"up":{"texture":"#front","uv":[5,5,11,11]},"west":{"texture":"#front","uv":[5,5,6,11]}},"from":[5,0.54505,9.29505],"rotation":{"angle":-45,"axis":"x","origin":[-4,0.04505,0.04505]},"to":[11,1.04505,15.29505]},{"faces":{"down":{"texture":"#front","uv":[6,6,10,10]},"east":{"rotation":90,"texture":"#front","uv":[9,6,10,10]},"north":{"texture":"#front","uv":[10,6,6,7]},"south":{"texture":"#front","uv":[6,9,10,10]},"up":{"texture":"#front","uv":[6,6,10,10]},"west":{"texture":"#front","uv":[6,6,7,10]}},"from":[6,8.11612,7.36612],"rotation":{"angle":-45,"axis":"x","origin":[-1,7.11612,7.11612]},"to":[10,8.61612,11.36612]}],"textures":{"front":"block/detector_rail_on","particle":"block/detector_rail_on"}}